gemini_agent/__init__.py
gemini_agent/_version.py
gemini_agent/client/__init__.py
gemini_agent/client/client.py
gemini_agent/core/__init__.py
gemini_agent/core/agent.py
gemini_agent/core/models.py
gemini_agent/server/__init__.py
gemini_agent/server/app.py
gemini_agent/server/config.py
gemini_agent/server/models.py
gemini_agent/server/worker.py
gemini_agent/server/routes/__init__.py
gemini_agent/server/routes/health.py
gemini_agent/server/routes/mcp.py
gemini_agent/server/routes/sessions.py
gemini_agent/server/routes/tasks.py
gemini_cli_agent-0.1.0.dist-info/licenses/LICENSE
gemini_cli_agent-0.1.0.dist-info/METADATA
gemini_cli_agent-0.1.0.dist-info/WHEEL
gemini_cli_agent-0.1.0.dist-info/entry_points.txt
gemini_cli_agent-0.1.0.dist-info/top_level.txt
gemini_cli_agent-0.1.0.dist-info/RECORD
