Metadata-Version: 2.4
Name: gemini-cli-agent
Version: 0.1.0
Summary: Python wrapper for Google's Gemini CLI agentic capabilities
Author-email: Saurav Chandra <mail@sauravchandra.com>
License: MIT
Project-URL: Homepage, https://github.com/sauravchandra/gemini-agent
Project-URL: Documentation, https://github.com/sauravchandra/gemini-agent#readme
Project-URL: Repository, https://github.com/sauravchandra/gemini-agent
Keywords: gemini,ai,agent,cli,mcp,google,llm
Classifier: Development Status :: 4 - Beta
Classifier: Intended Audience :: Developers
Classifier: License :: OSI Approved :: MIT License
Classifier: Programming Language :: Python :: 3
Classifier: Programming Language :: Python :: 3.11
Classifier: Programming Language :: Python :: 3.12
Classifier: Framework :: FastAPI
Classifier: Topic :: Software Development :: Libraries :: Python Modules
Requires-Python: >=3.11
License-File: LICENSE
Requires-Dist: httpx>=0.26.0
Provides-Extra: server
Requires-Dist: fastapi>=0.109.0; extra == "server"
Requires-Dist: uvicorn[standard]>=0.27.0; extra == "server"
Requires-Dist: celery[redis]>=5.3.0; extra == "server"
Requires-Dist: redis>=5.0.0; extra == "server"
Requires-Dist: pydantic>=2.6.0; extra == "server"
Requires-Dist: pydantic-settings>=2.1.0; extra == "server"
Requires-Dist: python-multipart>=0.0.9; extra == "server"
Provides-Extra: core
Provides-Extra: dev
Requires-Dist: pytest>=7.4.0; extra == "dev"
Requires-Dist: pytest-asyncio>=0.21.0; extra == "dev"
Requires-Dist: httpx>=0.26.0; extra == "dev"
Requires-Dist: black>=23.0.0; extra == "dev"
Requires-Dist: ruff>=0.1.0; extra == "dev"
Provides-Extra: all
Requires-Dist: gemini-cli-agent[server]; extra == "all"
Dynamic: license-file
